gbb/__init__.py
gbb/__main__.py
gbb/main.py
gbb/config/__init__.py
gbb/config/config.py
gbb/interpolation/__init__.py
gbb/interpolation/linear_interpolation3d.py
gbb/interpolation/nn_interpolation3d.py
gbb/io/__init__.py
gbb/io/get_filename.py
gbb/io/load_data.py
gbb/io/read_anchor.py
gbb/io/read_json.py
gbb/io/write_json.py
gbb/io/write_shift.py
gbb/neighbor/__init__.py
gbb/neighbor/nn_2d.py
gbb/neighbor/nn_3d.py
gbb/normal/__init__.py
gbb/normal/get_normal.py
gbb/normal/plot_normal.py
gbb/normal/plot_normal_direction.py
gbb/normal/plot_white2pial.py
gbb/plot/__init__.py
gbb/plot/anim_cost.py
gbb/plot/get_gif.py
gbb/plot/plot_cost.py
gbb/plot/plot_slope.py
gbb/process/__init__.py
gbb/process/run_anchor.py
gbb/process/run_devein.py
gbb/process/run_gbb.py
gbb/utils/__init__.py
gbb/utils/apply_deformation.py
gbb/utils/check_exit.py
gbb/utils/cost_BBR.py
gbb/utils/deformation_field.py
gbb/utils/get_adjm.py
gbb/utils/get_gradient.py
gbb/utils/get_ignore.py
gbb/utils/get_shift.py
gbb/utils/line_ras2vox.py
gbb/utils/remove_vertex.py
gbb/utils/smooth_surface.py
gbb/utils/update_mesh.py
gbb/utils/vox2ras.py
gbb-0.1.6.dist-info/LICENSE
gbb-0.1.6.dist-info/METADATA
gbb-0.1.6.dist-info/WHEEL
gbb-0.1.6.dist-info/top_level.txt
gbb-0.1.6.dist-info/RECORD
