Metadata-Version: 2.1
Name: gbb
Version: 0.1.6
Summary: Gradient-based boundary (GBB) surface refinement
Home-page: https://github.com/haenelt/GBB
Author: Daniel Haenelt
Author-email: daniel.haenelt@gmail.com
License: GPL v3
Platform: UNKNOWN
Classifier: Programming Language :: Python :: 3
Classifier: Programming Language :: Python :: 3.6
Classifier: Programming Language :: Python :: 3.7
Classifier: Programming Language :: Python :: 3.8
Classifier: License :: OSI Approved :: GNU General Public License v3 (GPLv3)
Classifier: Operating System :: OS Independent
Classifier: Development Status :: 3 - Alpha
Classifier: Intended Audience :: Science/Research
Classifier: Topic :: Scientific/Engineering
Requires-Python: >=3.6
Requires-Dist: numpy
Requires-Dist: nibabel
Requires-Dist: scipy
Requires-Dist: matplotlib
Requires-Dist: imageio
Requires-Dist: opencv-python
